bsheets/__init__.py
bsheets/excel.py
bsheets-0.1.2.dist-info/METADATA
bsheets-0.1.2.dist-info/RECORD
bsheets-0.1.2.dist-info/WHEEL
bsheets-0.1.2.dist-info/top_level.txt
