Metadata-Version: 2.1
Name: bsheets
Version: 0.1.2
Summary: Library for working with spreadsheets
Home-page: https://github.com/BlackEarth/bsheets
Author: Sean Harrison
Author-email: sah@bookgenesis.com
License: MPL 2.0
Platform: UNKNOWN
Classifier: Development Status :: 4 - Beta
Classifier: Intended Audience :: Developers
Classifier: License :: OSI Approved :: Mozilla Public License 2.0 (MPL 2.0)
Classifier: Programming Language :: Python :: 3
Provides-Extra: test
Provides-Extra: dev
Requires-Dist: openpyxl
Requires-Dist: cchardet
Provides-Extra: dev
Requires-Dist: twine; extra == 'dev'
Provides-Extra: test
